[{"abbr":"LEAD","name":"leader"},{"abbr":"WELF","name":"wood elf"},{"abbr":"HELF","name":"high elf"},{"abbr":"IDWA","name":"ice dwarf"},{"abbr":"HDWA","name":"hill dwarf"},{"abbr":"UDWA","name":"under dwarf"},{"abbr":"ORC","name":"orc"},{"abbr":"GNOM","name":"gnome"},{"abbr":"CTAU","name":"centaur"},{"abbr":"HERB","name":"herb"},{"abbr":"HORS","name":"horse"},{"abbr":"SWOR","name":"sword"},{"abbr":"XBOW","name":"crossbow"},{"abbr":"LBOW","name":"longbow"},{"abbr":"CARM","name":"chain armor"},{"abbr":"PARM","name":"plate armor"},{"abbr":"WING","name":"winged horse"},{"abbr":"MSWO","name":"mithril sword"},{"abbr":"MARM","name":"mithril armor"},{"abbr":"DBOW","name":"double bow"},{"abbr":"LION","name":"lion"},{"abbr":"WOLF","name":"wolf"},{"abbr":"GRIZ","name":"grizzly bear"},{"abbr":"CROC","name":"crocodile"},{"abbr":"ANAC","name":"anaconda"},{"abbr":"SCOR","name":"giant scorpion"},{"abbr":"POLA","name":"polar bear"},{"abbr":"GRAT","name":"giant rat"},{"abbr":"GSPI","name":"giant spider"},{"abbr":"GLIZ","name":"giant lizard"},{"abbr":"TREN","name":"trent"},{"abbr":"ROC","name":"roc"},{"abbr":"BOGT","name":"bog thing"},{"abbr":"KONG","name":"kong"},{"abbr":"SPHI","name":"sphinx"},{"abbr":"ICEW","name":"ice wurm"},{"abbr":"DRAG","name":"dragon"},{"abbr":"CENT","name":"centaur"},{"abbr":"KOBO","name":"kobold"},{"abbr":"OGRE","name":"ogre"},{"abbr":"LMAN","name":"lizard man"},{"abbr":"WMAN","name":"wild man"},{"abbr":"SAND","name":"sandling"},{"abbr":"YETI","name":"yeti"},{"abbr":"GOBL","name":"goblin"},{"abbr":"TROL","name":"troll"},{"abbr":"ETTI","name":"ettin"},{"abbr":"SKEL","name":"skeleton"},{"abbr":"UNDE","name":"undead"},{"abbr":"LICH","name":"lich"},{"abbr":"IMP","name":"imp"},{"abbr":"DEMO","name":"demon"},{"abbr":"BALR","name":"balrog"},{"abbr":"EAGL","name":"eagle"},{"abbr":"XXXX","name":"amulet of invulnerability"},{"abbr":"CLOA","name":"cloak of invulnerability"},{"abbr":"STAF","name":"staff of fire"},{"abbr":"AMPR","name":"amulet of protection"},{"abbr":"RUNE","name":"runesword"},{"abbr":"SHST","name":"shieldstone"},{"abbr":"iWOLF","name":"illusory wolf"},{"abbr":"iEAGL","name":"illusory eagle"},{"abbr":"iDRAG","name":"illusory dragon"},{"abbr":"iSKEL","name":"illusory skeleton"},{"abbr":"iUNDE","name":"illusory undead"},{"abbr":"iLICH","name":"illusory lich"},{"abbr":"iIMP","name":"illusory imp"},{"abbr":"iDEMO","name":"illusory demon"},{"abbr":"iBALR","name":"illusory balrog"},{"abbr":"PICK","name":"pick"},{"abbr":"SPEA","name":"spear"},{"abbr":"AXE","name":"axe"},{"abbr":"HAMM","name":"hammer"},{"abbr":"MXBO","name":"magic crossbow"},{"abbr":"LARM","name":"leather armor"},{"abbr":"CLAR","name":"cloth armor"},{"abbr":"PIRA","name":"pirates"},{"abbr":"KRAK","name":"kraken"},{"abbr":"MERF","name":"merfolk"},{"abbr":"ELEM","name":"elemental"},{"abbr":"HUMN","name":"human"},{"abbr":"LIZA","name":"lizardman"},{"abbr":"GBLN","name":"goblin"},{"abbr":"GNOL","name":"gnoll"},{"abbr":"DRLF","name":"drow elf"},{"abbr":"BAXE","name":"battle axe"},{"abbr":"MBAX","name":"mithril battle axe"},{"abbr":"ASWR","name":"admantium sword"},{"abbr":"ABAX","name":"admantium battle axe"},{"abbr":"ARNG","name":"admantium ring mail"},{"abbr":"AARM","name":"admantium plate mail"},{"abbr":"CAME","name":"camel"},{"abbr":"DROW","name":"drow warrior"},{"abbr":"HYDR","name":"hydra"},{"abbr":"STGI","name":"storm giant"},{"abbr":"CLGI","name":"cloud giant"},{"abbr":"ILLY","name":"illyrthid"},{"abbr":"SORC","name":"evil sorcerer"},{"abbr":"MAGI","name":"evil magician"},{"abbr":"DMAG","name":"dark mage"},{"abbr":"WARR","name":"evil warrior"},{"abbr":"IDRA","name":"ice dragon"},{"abbr":"HPOT","name":"healing potion"},{"abbr":"JAVE","name":"javelin"},{"abbr":"FSWO","name":"flaming sword"},{"abbr":"MSHD","name":"mithril shield"},{"abbr":"ISHD","name":"iron shield"},{"abbr":"WSHD","name":"wooden shield"},{"abbr":"STAH","name":"staff of healing"},{"abbr":"BKEX","name":"book of exorcism"},{"abbr":"HLYS","name":"holy symbol"},{"abbr":"CNSR","name":"censer of protection"},{"abbr":"TURT","name":"giant turtle"},{"abbr":"CATP","name":"catapult"},{"abbr":"STED","name":"steel defender"},{"abbr":"ADRG","name":"admantium dragon"}]