{
  "attackers": {
    "units": [
      {
        "name": "Unit",
        "skills": [
          {
            "abbr": "FIRE",
            "level": 1
          }
        ],
        "items": [
          {
            "abbr": "DRAG",
            "amount": 4
          },
          {
            "abbr": "LEAD",
            "amount": 1
          }
        ],
        "flags": [
          "behind"
        ],
        "combatSpell": "FIRE"
      }
    ]
  },
  "defenders": {
    "units": [
      {
        "name": "Unit",
        "skills": [],
        "items": [
          {
            "abbr": "BALR",
            "amount": 1
          }
        ]
      }
    ]
  }
}